Ketzal/Ketzal.py
Ketzal/__init__.py
Ketzal/src/cli/__init__.py
Ketzal/src/cli/new.py
Ketzal/src/cli/run.py
Ketzal/src/config/__init__.py
Ketzal/src/config/config.py
Ketzal/src/http/HttpMethod.py
Ketzal/src/http/__init__.py
Ketzal/src/routing/RouteDefinition.py
Ketzal/src/routing/Router.py
Ketzal/src/routing/__init__.py
Ketzal/src/server/FileWatcher.py
Ketzal/src/server/RequestHandler.py
Ketzal/src/server/RouteLoader.py
Ketzal/src/server/SocketManager.py
Ketzal/src/server/__init__.py
Ketzal/src/server/server.py
Ketzal/src/util/structure.py
Ketzal/src/view/__init__.py
Ketzal/src/view/view.py
ketzal-0.1.1.dist-info/METADATA
ketzal-0.1.1.dist-info/WHEEL
ketzal-0.1.1.dist-info/entry_points.txt
ketzal-0.1.1.dist-info/top_level.txt
ketzal-0.1.1.dist-info/RECORD
