Metadata-Version: 2.4
Name: Ketzal
Version: 0.1.1
Summary: Experimental framework inspired by Laravel
Author-email: Héctor <danielramirezr27@gmail.com>
License: MIT
Keywords: framework,web,ketzal,laravel-like
Classifier: Programming Language :: Python :: 3
Classifier: License :: OSI Approved :: MIT License
Classifier: Operating System :: OS Independent
Requires-Python: >=3.12
Requires-Dist: rich>=12.0.0
Requires-Dist: click>=8.1.3
Requires-Dist: watchdog>=6.0.0
Requires-Dist: python-dotenv>=1.1.1
